xflat
