Metadata-Version: 1.0
Name: xflat
Version: 0.0.3
Summary: Flattens xml/html documents
Home-page: https://github.com/oskarnyqvists/xflat
Author: oskarnyqvist
Author-email: oskarnyqvist@gmail.com
License: The MIT License (MIT)
